empm/__init__.py
empm/__main__.py
empm/utility.py
empm/_internal/cli/__init__.py
empm/_internal/cli/main.py
empm/_internal/command/__init__.py
empm/_internal/command/add.py
empm/_internal/command/home.py
empm/_internal/command/install.py
empm/_internal/command/remove.py
empm/_internal/utility/__init__.py
empm/_internal/web/__init__.py
empm/_internal/web/main.py
empm/_internal/web/frontend/dist/index.html
empm/_internal/web/frontend/dist/assets/index-0OYeglMF.css
empm/_internal/web/frontend/dist/assets/index-DXTHNBf0.js
test/__init__.py
test/test_cli.py
test/test_utility.py
test/test_web.py
test/utility/__init__.py
test/utility/env_manage.py
empm-0.0.12.dist-info/LICENSE
empm-0.0.12.dist-info/METADATA
empm-0.0.12.dist-info/WHEEL
empm-0.0.12.dist-info/entry_points.txt
empm-0.0.12.dist-info/top_level.txt
empm-0.0.12.dist-info/RECORD
