Metadata-Version: 2.1
Name: empm
Version: 0.0.12
Summary: embedded pack manage
Author-email: paopaozhi <paopaozhi@hotmail.com>, hymn <hexinyi136@139.com>
Project-URL: Homepage, https://github.com/paopaozhi/cepack
Project-URL: Bug Tracker, https://github.com/paopaozhi/cepack/issues
Classifier: Programming Language :: Python :: 3.9
Classifier: License :: OSI Approved :: Apache Software License
Classifier: Operating System :: OS Independent
Requires-Python: >=3.9
License-File: LICENSE
Requires-Dist: typer
Requires-Dist: toml
Requires-Dist: requests
Requires-Dist: fastapi
